{
    "basics":{
    "name": "Muhammad Shayan Nazeer",
    "label": "Graduate Research Assistant",
    "email": "mnazeer@umass.edu",
    "phone": "(413) 466-1903",
    "url": "mshayannazeer.github.io",
    "location": {
      "address": "151 Holdsworthway",
      "postalCode": "MA 01003",
      "city": "Amherst",
      "countryCode": "US",
      "region": "Massachusetts"
    },
        "profiles": [
      {
        "network": "LinkedIn",
        "url": "https://www.linkedin.com/in/m-shayan-nazeer/"
      }
    ]
    },
    "education": [
        {
            "institution": "University of Massachusetts, Amherst",
            "startDate": "2023.09",
            "studyType": "Doctor of Philosophy (Ph.D.)",
            "location": "Amherst, MA, USA",
            "area": "Electrical and Computer Engineering",
            "advisor": "Dr. Muhammad Taqi Raza"
        },
        {
            "institution": "National University of Sciences and Technology (NUST)",
            "startDate": "2019.09",
            "endDate": "2023.06",
            "studyType": "Bachelor of Engineering",
            "area": "Electrical Engineering",
            "distinction": "Gold Medalist",
            "location": "Islamabad, Pakistan",
            "focus_area": "Embedded systems, Hardware Security, wireless communication",
            "final_year_project": {
                "title": "Extensive Python library for implementing state-of-the-art logic locking techniques",
                "description": "Empowering users to implement hardware security techniques on verilog hardware designs effortlessly.",
                "advisors": [
                    "Dr. Muhammad Shafique",
                    "Dr. Rehan Ahmed"
                ]
            }
        }
    ],
    "work": [
        {
            "name": "University of Massachusetts Amherst",
            "startDate": "2023.09",
            "position": "Graduate Research Assistant",
            "location": "Amherst, MA, USA",
            "summary": [
                "Developed a distributed 5G core testbed on the POWDER platform by the University of Utah.",
                "Separated user and control planes within the testbed for enhanced experimentation and comprehensive insights.",
                "Testing developed testbed under various test cases by deploying simulated UEs (User Equipment) to evaluate distributed 5G core."
            ]
        },
        {
            "name": "EEG Research Lab SEECS",
            "startDate": "2022.09",
            "endDate": "2023.06",
            "position": "Research Assistant",
            "location": "Islamabad, Pakistan",
            "project_title": "A Brain-Computer Interface (BCI) Enabled Motion Intent Recognition System for Assistive Robotics",
            "summary": [
                "Won a research grant of PKR 1 million for the project from my university.",
                "Trained and developed an EEG classifier using parallel CNNs and RNNs to predict the intention of left, right, up, and down movements with the accuracy of 89%.",
                "Integrated a robotic arm to be controlled using prediction from EEG classifier."
            ]
        },
        {
            "name": "RADWI Pvt. Ltd.",
            "startDate": "2021.04",
            "endDate": "2023.10",
            "position": "Home Automation Engineer (Internship)",
            "location": "Islamabad, Pakistan",
            "summary": [
                "Designed and developed various home automation devices including smart switches and automated lights.",
                "Prototyped complete working system for IoT-enabled electronic door lock.",
                "Developed a specialized PCB for each device using Altium Designer.",
                "Integrated smart home devices with AWS IoT core to allow for connectivity through smartphones over the internet."
            ]
        }
    ]
    


}
